pylattice/__init__.py
pylattice/classes/Track.py
pylattice/classes/TrackUnprocessed.py
pylattice/classes/__init__.py
pylattice/functions/DataAnalysis.py
pylattice/functions/InputProcessing.py
pylattice/functions/InterfaceChimeraX.py
pylattice/functions/TiffBoxDrawing.py
pylattice/functions/TiffProcessing.py
pylattice/functions/__init__.py
pylattice-0.1.3.dist-info/METADATA
pylattice-0.1.3.dist-info/RECORD
pylattice-0.1.3.dist-info/WHEEL
pylattice-0.1.3.dist-info/top_level.txt
