Metadata-Version: 2.1
Name: pylattice
Version: 0.1.3
Summary: A python library for lattice light-sheet image analysis
Home-page: https://github.com/JohSchoeneberg/pyLattice
Author: Joh Schoeneberg
Author-email: joh@schoeneberglab.org
License: UNKNOWN
Platform: UNKNOWN
Classifier: Programming Language :: Python :: 3
Classifier: License :: OSI Approved :: BSD License
Classifier: Operating System :: OS Independent
Classifier: Topic :: Scientific/Engineering
